setup.cfg
setup.py
pyzmqrpc.egg-info/PKG-INFO
pyzmqrpc.egg-info/SOURCES.txt
pyzmqrpc.egg-info/dependency_links.txt
pyzmqrpc.egg-info/requires.txt
pyzmqrpc.egg-info/top_level.txt
zmqrpc/ZmqProxy.py
zmqrpc/ZmqReceiver.py
zmqrpc/ZmqRpcClient.py
zmqrpc/ZmqRpcServer.py
zmqrpc/ZmqSender.py
zmqrpc/__init__.py