Metadata-Version: 1.1
Name: pyzmqrpc
Version: 1.0.1
Summary: A simple ZMQ RPC extension with JSON for message serialization
Home-page: https://github.com/jverhoeven/pyzmqrpc
Author: J Verhoeven
Author-email: jan@visity.nl
License: UNKNOWN
Download-URL: https://github.com/jverhoeven/pyzmqrpc/tarball/1.0.0
Keywords: zeromq,rpc,pyzmq
Platform: UNKNOWN
